dysession/__init__.py
dysession/admin.py
dysession/apps.py
dysession/middleware.py
dysession/settings.py
dysession/version.txt
dysession/aws/__init__.py
dysession/aws/dynamodb.py
dysession/aws/error.py
dysession/backends/__init__.py
dysession/backends/db.py
dysession/backends/error.py
dysession/backends/model.py
dysession/logger/__init__.py
dysession/logger/handler/__init__.py
dysession/logger/handler/ansi.py
dysession/logger/handler/colorful_console.py
dysession/management/__init__.py
dysession/management/commands/__init__.py
dysession/management/commands/_arg_types.py
dysession/management/commands/dysession_clear.py
dysession/management/commands/dysession_destory.py
dysession/management/commands/dysession_init.py
tests/__init__.py
tests/test_admin.py
tests/test_apps.py
tests/test_aws_dynamodb.py
tests/test_backend_db.py
tests/test_backend_model.py
tests/test_command_arg_types.py
tests/test_commands.py
tests/test_logger.py
tests/test_logger_handler_ansi.py
tests/test_settings.py
django_dysession-1.1.1.dist-info/LICENSE
django_dysession-1.1.1.dist-info/METADATA
django_dysession-1.1.1.dist-info/WHEEL
django_dysession-1.1.1.dist-info/top_level.txt
django_dysession-1.1.1.dist-info/RECORD
