Metadata-Version: 2.1
Name: django-dysession
Version: 1.1.1
Summary: "django-dysession is a django extension which integrated AWS DynamoDB as a session backend"
Home-page: https://github.com/MissterHao/django-dysession/releases/latest/download/django-dysession.tar.gz
Download-URL: https://github.com/MissterHao/django-dysession/releases/latest/download/django-dysession.tar.gz
Author: "Hao-Wei, Li"
Author-email: "henryliking@gmail.com"
Maintainer: "MissterHao"
Maintainer-email: "henryliking@gmail.com"
License: MIT
Keywords: "django,session,aws,dynamodb"
Classifier: Development Status :: 5 - Production/Stable
Classifier: Environment :: Web Environment
Classifier: Framework :: Django
Classifier: Framework :: Django :: 3.2
Classifier: Framework :: Django :: 4
Classifier: Framework :: Django :: 4.0
Classifier: Framework :: Django :: 4.1
Classifier: Intended Audience :: Developers
Classifier: License :: OSI Approved :: MIT License
Classifier: Operating System :: OS Independent
Classifier: Programming Language :: Python :: 3.10
Classifier: Programming Language :: Python :: 3.9
Classifier: Programming Language :: Python :: 3.8
Classifier: Programming Language :: Python :: Implementation
Classifier: Topic :: Software Development :: Libraries :: Application Frameworks
Classifier: Topic :: Software Development :: Libraries :: Python Modules
Classifier: Topic :: Internet :: WWW/HTTP :: Session
Classifier: Topic :: Security
Classifier: Topic :: Database
Requires-Python: >=3.8
License-File: LICENSE
Requires-Dist: Django (>=3.2)
Requires-Dist: boto3 (>=1.26.59)
